model_inference_fastapi/__init__.py
model_inference_fastapi/main.py
model_inference_fastapi/model_service.py
model_inference_fastapi/model_service_base.py
model_inference_fastapi/utils.py
model_inference_fastapi-0.0.1a0.dist-info/METADATA
model_inference_fastapi-0.0.1a0.dist-info/WHEEL
model_inference_fastapi-0.0.1a0.dist-info/licenses/LICENSE
model_inference_fastapi-0.0.1a0.dist-info/RECORD
