Metadata-Version: 2.1
Name: model-inference-fastapi
Version: 0.0.1a0
Summary: Use fastapi for model inference over http
Project-URL: Homepage, https://https://github.com/robotstech/model-inference-fastapi
Project-URL: Repository, https://https://github.com/robotstech/model-inference-fastapi.git
Project-URL: Bug Tracker, https://github.com/robotstech/model-inference-fastapi/issues
Author-email: iamr0b0tx <tech@robotslimited.com>
Maintainer-email: iamr0b0tx <tech@robotslimited.com>
License: MIT License
License-File: LICENSE
Keywords: api,deep learning,deploy,inference,machine learning
Classifier: Environment :: Console
Classifier: Intended Audience :: Developers
Classifier: Intended Audience :: Education
Classifier: Intended Audience :: Information Technology
Classifier: Intended Audience :: Science/Research
Classifier: License :: OSI Approved :: MIT License
Classifier: Natural Language :: English
Classifier: Operating System :: OS Independent
Classifier: Programming Language :: Python :: 3
Classifier: Programming Language :: Python :: 3 :: Only
Classifier: Programming Language :: Python :: 3.8
Classifier: Programming Language :: Python :: 3.9
Classifier: Programming Language :: Python :: 3.10
Classifier: Programming Language :: Python :: 3.11
Classifier: Topic :: Scientific/Engineering
Classifier: Topic :: Scientific/Engineering :: Artificial Intelligence
Classifier: Topic :: Scientific/Engineering :: Mathematics
Classifier: Topic :: Software Development
Classifier: Topic :: Software Development :: Libraries
Classifier: Topic :: Software Development :: Libraries :: Python Modules
Requires-Python: >=3.7
Requires-Dist: fastapi>=0.94.0
Requires-Dist: pillow>=9.4.0
Requires-Dist: python-multipart>=0.0.6
Requires-Dist: uvicorn[standard]>=0.21.0
